{
  "metadata": {
    "version": "3.0.0",
    "lastUpdated": "2025-02-15",
    "totalMods": 304,
    "totalMachines": 2000,
    "textureSource": "https://github.com/GTNewHorizons"
  },
  "modList": [
    {"name": "GT5-Unofficial", "repo": "GT5-Unofficial", "category": "core", "machines": 500, "hasTextures": true},
    {"name": "Applied Energistics 2", "repo": "Applied-Energistics-2-Unofficial", "category": "tech", "machines": 80, "hasTextures": true},
    {"name": "Tinkers Construct", "repo": "TinkersConstruct", "category": "tools", "machines": 25, "hasTextures": true},
    {"name": "EnderIO", "repo": "EnderIO", "category": "tech", "machines": 50, "hasTextures": true},
    {"name": "Forestry", "repo": "ForestryMC", "category": "farming", "machines": 40, "hasTextures": true},
    {"name": "Railcraft", "repo": "Railcraft", "category": "transport", "machines": 35, "hasTextures": true},
    {"name": "Galacticraft", "repo": "Galacticraft", "category": "space", "machines": 45, "hasTextures": true},
    {"name": "Blood Magic", "repo": "BloodMagic", "category": "magic", "machines": 30, "hasTextures": true},
    {"name": "Botania", "repo": "Botania", "category": "magic", "machines": 50, "hasTextures": true},
    {"name": "Thaumcraft", "repo": "Salis-Arcana", "category": "magic", "machines": 60, "hasTextures": true},
    {"name": "Draconic Evolution", "repo": "Draconic-Evolution", "category": "endgame", "machines": 25, "hasTextures": true},
    {"name": "Avaritia", "repo": "Avaritia", "category": "endgame", "machines": 15, "hasTextures": true},
    {"name": "OpenComputers", "repo": "OpenComputers", "category": "tech", "machines": 35, "hasTextures": true},
    {"name": "Buildcraft", "repo": "BuildCraft", "category": "tech", "machines": 30, "hasTextures": true},
    {"name": "Project Red", "repo": "ProjectRed", "category": "redstone", "machines": 40, "hasTextures": true},
    {"name": "Chisel", "repo": "Chisel", "category": "decoration", "machines": 5, "hasTextures": true},
    {"name": "Binnie's Mods", "repo": "Binnie", "category": "farming", "machines": 20, "hasTextures": true},
    {"name": "Magic Bees", "repo": "MagicBees", "category": "magic", "machines": 10, "hasTextures": true},
    {"name": "Gendustry", "repo": "gendustry", "category": "farming", "machines": 15, "hasTextures": true},
    {"name": "Extra Utilities", "repo": "Extra-Utilities", "category": "utility", "machines": 30, "hasTextures": true},
    {"name": "Twilight Forest", "repo": "twilightforest", "category": "dimension", "machines": 10, "hasTextures": true},
    {"name": "Forbidden Magic", "repo": "ForbiddenMagic", "category": "magic", "machines": 15, "hasTextures": true},
    {"name": "Thaumic Energistics", "repo": "ThaumicEnergistics", "category": "magic", "machines": 20, "hasTextures": true},
    {"name": "Witching Gadgets", "repo": "WitchingGadgets", "category": "magic", "machines": 15, "hasTextures": true},
    {"name": "Thaumic Tinkerer", "repo": "ThaumicTinkerer", "category": "magic", "machines": 20, "hasTextures": true},
    {"name": "Gadomancy", "repo": "Gadomancy", "category": "magic", "machines": 15, "hasTextures": true},
    {"name": "Electro-Magic Tools", "repo": "Electro-Magic-Tools", "category": "magic", "machines": 10, "hasTextures": true},
    {"name": "Nuclear Control", "repo": "Nuclear-Control", "category": "tech", "machines": 15, "hasTextures": true},
    {"name": "GT++", "repo": "GTplusplus", "category": "core", "machines": 100, "hasTextures": true},
    {"name": "Hardcore Ender Expansion", "repo": "Hardcore-Ender-Expansion", "category": "dimension", "machines": 20, "hasTextures": true},
    {"name": "Storage Drawers", "repo": "StorageDrawers", "category": "storage", "machines": 10, "hasTextures": true},
    {"name": "JABBA", "repo": "Jabba", "category": "storage", "machines": 5, "hasTextures": true},
    {"name": "Iron Tanks", "repo": "Irontanks", "category": "storage", "machines": 10, "hasTextures": true},
    {"name": "Iron Chests", "repo": "ironchest", "category": "storage", "machines": 10, "hasTextures": true},
    {"name": "Better Questing", "repo": "BetterQuesting", "category": "utility", "machines": 5, "hasTextures": true},
    {"name": "Logistics Pipes", "repo": "LogisticsPipes", "category": "logistics", "machines": 30, "hasTextures": true},
    {"name": "AE2 Stuff", "repo": "ae2stuff", "category": "tech", "machines": 10, "hasTextures": true},
    {"name": "Steve's Factory Manager", "repo": "Steve-s-Factory-Manager", "category": "automation", "machines": 5, "hasTextures": true},
    {"name": "Open Blocks", "repo": "OpenBlocks", "category": "utility", "machines": 25, "hasTextures": true},
    {"name": "Carpenters Blocks", "repo": "CarpentersBlocks", "category": "decoration", "machines": 15, "hasTextures": true},
    {"name": "Architecture Craft", "repo": "ArchitectureCraft", "category": "decoration", "machines": 10, "hasTextures": true},
    {"name": "Natura", "repo": "Natura", "category": "world", "machines": 5, "hasTextures": true},
    {"name": "Malisis Doors", "repo": "MalisisDoors", "category": "decoration", "machines": 10, "hasTextures": true},
    {"name": "Ender Storage", "repo": "EnderStorage", "category": "storage", "machines": 5, "hasTextures": true},
    {"name": "Wireless Crafting Terminal", "repo": "WirelessCraftingTerminal", "category": "tech", "machines": 5, "hasTextures": true},
    {"name": "SGCraft", "repo": "SGCraft", "category": "transport", "machines": 10, "hasTextures": true},
    {"name": "Computronics", "repo": "Computronics", "category": "tech", "machines": 15, "hasTextures": true},
    {"name": "HBM Nuclear Tech", "repo": "Hbm-s-Nuclear-Tech-GIT", "category": "tech", "machines": 50, "hasTextures": true},
    {"name": "Crops++", "repo": "Crops-plus-plus", "category": "farming", "machines": 10, "hasTextures": true},
    {"name": "Visual Prospecting", "repo": "VisualProspecting", "category": "utility", "machines": 2, "hasTextures": true},
    {"name": "Matter Manipulator", "repo": "MatterManipulator", "category": "utility", "machines": 5, "hasTextures": true},
    {"name": "Adventure Backpack", "repo": "AdventureBackpack2", "category": "utility", "machines": 3, "hasTextures": true},
    {"name": "Hydro Energy", "repo": "HydroEnergy", "category": "power", "machines": 10, "hasTextures": true},
    {"name": "Flood Lights", "repo": "FloodLights", "category": "utility", "machines": 5, "hasTextures": true},
    {"name": "Little Tiles", "repo": "LittleTiles", "category": "decoration", "machines": 5, "hasTextures": true},
    {"name": "Open Modular Turrets", "repo": "OpenModularTurrets", "category": "defense", "machines": 15, "hasTextures": true},
    {"name": "The Aether", "repo": "The-Aether-GTNH", "category": "dimension", "machines": 20, "hasTextures": true},
    {"name": "Amun-Ra", "repo": "amunra", "category": "space", "machines": 30, "hasTextures": true},
    {"name": "Galaxia", "repo": "Galaxia", "category": "space", "machines": 25, "hasTextures": true},
    {"name": "Super Solar Panels", "repo": "supersolarpanels", "category": "power", "machines": 10, "hasTextures": true},
    {"name": "Gravitation Suite", "repo": "Gravitation-Suite-Neo", "category": "armor", "machines": 5, "hasTextures": true},
    {"name": "Twist Space Technology", "repo": "Twist-Space-Technology-Mod", "category": "tech", "machines": 30, "hasTextures": true},
    {"name": "Box++", "repo": "BoxPlusPlus", "category": "utility", "machines": 5, "hasTextures": true},
    {"name": "Et Futurum", "repo": "Et-Futurum-Requiem", "category": "utility", "machines": 10, "hasTextures": true},
    {"name": "Tainted Magic", "repo": "Tainted-Magic", "category": "magic", "machines": 10, "hasTextures": true},
    {"name": "Thaumic Bases", "repo": "ThaumicBases", "category": "magic", "machines": 10, "hasTextures": true},
    {"name": "Thaumic Horizons", "repo": "ThaumicHorizons", "category": "magic", "machines": 15, "hasTextures": true},
    {"name": "Advanced Botany", "repo": "Advanced-Botany", "category": "magic", "machines": 10, "hasTextures": true},
    {"name": "Blood Arsenal", "repo": "BloodArsenal", "category": "magic", "machines": 10, "hasTextures": true},
    {"name": "Botanic Horizons", "repo": "Botanic-horizons", "category": "magic", "machines": 10, "hasTextures": true},
    {"name": "Eternal Singularity", "repo": "Eternal-Singularity", "category": "endgame", "machines": 5, "hasTextures": true},
    {"name": "Universal Singularities", "repo": "Universal-Singularities", "category": "endgame", "machines": 5, "hasTextures": true},
    {"name": "Avaritiaddons", "repo": "Avaritiaddons", "category": "endgame", "machines": 5, "hasTextures": true},
    {"name": "Nuclear Horizons", "repo": "NuclearHorizons", "category": "tech", "machines": 15, "hasTextures": true},
    {"name": "Cooking For Blockheads", "repo": "CookingForBlockheads", "category": "utility", "machines": 10, "hasTextures": true},
    {"name": "Spice of Life", "repo": "SpiceOfLife", "category": "utility", "machines": 5, "hasTextures": true},
    {"name": "Warp Theory", "repo": "WarpTheory", "category": "magic", "machines": 5, "hasTextures": true},
    {"name": "Random Things", "repo": "Random-Things", "category": "utility", "machines": 20, "hasTextures": true},
    {"name": "Loot Games", "repo": "LootGames", "category": "utility", "machines": 5, "hasTextures": true},
    {"name": "Tinkerers Gregworks", "repo": "TinkersGregworks", "category": "tools", "machines": 10, "hasTextures": true},
    {"name": "Iguanas Tinkers Tweaks", "repo": "IguanaTweaksTConstruct", "category": "tools", "machines": 5, "hasTextures": true},
    {"name": "Super TiC", "repo": "Super-TiC", "category": "tools", "machines": 5, "hasTextures": true},
    {"name": "Tinkers Defense", "repo": "Tinkers-Defense", "category": "tools", "machines": 5, "hasTextures": true},
    {"name": "Tinkers Mechworks", "repo": "TinkersMechworks", "category": "tools", "machines": 10, "hasTextures": true},
    {"name": "NEI Addons", "repo": "neiaddons", "category": "utility", "machines": 0, "hasTextures": false},
    {"name": "WAILA", "repo": "waila", "category": "utility", "machines": 0, "hasTextures": false},
    {"name": "Journey Map", "repo": "journeymap-legacy", "category": "utility", "machines": 0, "hasTextures": false},
    {"name": "Hodgepodge", "repo": "Hodgepodge", "category": "core", "machines": 0, "hasTextures": false},
    {"name": "New Horizons Core Mod", "repo": "NewHorizonsCoreMod", "category": "core", "machines": 50, "hasTextures": true},
    {"name": "GTNH Lib", "repo": "GTNHLib", "category": "core", "machines": 0, "hasTextures": false},
    {"name": "AE2 Fluid Craft", "repo": "AE2FluidCraft-Rework", "category": "tech", "machines": 15, "hasTextures": true},
    {"name": "Not Enough Energistics", "repo": "NotEnoughEnergistics", "category": "tech", "machines": 5, "hasTextures": true},
    {"name": "Better P2P", "repo": "BetterP2P", "category": "tech", "machines": 5, "hasTextures": true},
    {"name": "Structure Lib", "repo": "StructureLib", "category": "core", "machines": 0, "hasTextures": false},
    {"name": "Modular UI", "repo": "ModularUI", "category": "core", "machines": 0, "hasTextures": false},
    {"name": "Angelica", "repo": "Angelica", "category": "core", "machines": 0, "hasTextures": false},
    {"name": "Roguelike Dungeons", "repo": "Roguelike-Dungeons", "category": "world", "machines": 0, "hasTextures": false},
    {"name": "Antique Atlas", "repo": "AntiqueAtlas", "category": "utility", "machines": 0, "hasTextures": false},
    {"name": "Astral Sorcery", "repo": "AstralSorcery", "category": "magic", "machines": 30, "hasTextures": true},
    {"name": "Schematica", "repo": "Schematica", "category": "utility", "machines": 0, "hasTextures": false},
    {"name": "Infernal Mobs", "repo": "Infernal-Mobs", "category": "world", "machines": 0, "hasTextures": false},
    {"name": "Special Mobs", "repo": "SpecialMobs", "category": "world", "machines": 0, "hasTextures": false},
    {"name": "Ender Zoo", "repo": "EnderZoo", "category": "world", "machines": 0, "hasTextures": false}
  ],
  "textureUrls": {
    "gregtech": "https://raw.githubusercontent.com/GTNewHorizons/GT5-Unofficial/master/src/main/resources/assets/gregtech/textures/blocks/iconsets/",
    "ae2": "https://raw.githubusercontent.com/GTNewHorizons/Applied-Energistics-2-Unofficial/master/src/main/resources/assets/appliedenergistics2/textures/blocks/",
    "tinkers": "https://raw.githubusercontent.com/GTNewHorizons/TinkersConstruct/master/src/main/resources/assets/tinker/textures/blocks/",
    "enderio": "https://raw.githubusercontent.com/GTNewHorizons/EnderIO/master/src/main/resources/assets/enderio/textures/blocks/",
    "forestry": "https://raw.githubusercontent.com/GTNewHorizons/ForestryMC/master/src/main/resources/assets/forestry/textures/blocks/",
    "railcraft": "https://raw.githubusercontent.com/GTNewHorizons/Railcraft/master/src/main/resources/assets/railcraft/textures/blocks/",
    "galacticraft": "https://raw.githubusercontent.com/GTNewHorizons/Galacticraft/master/src/main/resources/assets/galacticraftcore/textures/blocks/",
    "bloodmagic": "https://raw.githubusercontent.com/GTNewHorizons/BloodMagic/master/src/main/resources/assets/alchemicalwizardry/textures/blocks/",
    "botania": "https://raw.githubusercontent.com/GTNewHorizons/Botania/master/src/main/resources/assets/botania/textures/blocks/",
    "thaumcraft": "https://raw.githubusercontent.com/GTNewHorizons/Salis-Arcana/master/src/main/resources/assets/thaumcraft/textures/blocks/",
    "draconic": "https://raw.githubusercontent.com/GTNewHorizons/Draconic-Evolution/master/src/main/resources/assets/draconicevolution/textures/blocks/",
    "opencomputers": "https://raw.githubusercontent.com/GTNewHorizons/OpenComputers/master/src/main/resources/assets/opencomputers/textures/blocks/",
    "buildcraft": "https://raw.githubusercontent.com/GTNewHorizons/BuildCraft/master/src/main/resources/assets/buildcraft/textures/blocks/"
  },
  "categories": {
    "core": {"nameFr": "Mods Principaux", "color": "#FF6600", "count": 6},
    "tech": {"nameFr": "Technologie", "color": "#00BFFF", "count": 25},
    "magic": {"nameFr": "Magie", "color": "#9400D3", "count": 18},
    "tools": {"nameFr": "Outils", "color": "#FF4500", "count": 6},
    "farming": {"nameFr": "Agriculture/Abeilles", "color": "#8B4513", "count": 5},
    "storage": {"nameFr": "Stockage", "color": "#DAA520", "count": 6},
    "transport": {"nameFr": "Transport", "color": "#696969", "count": 3},
    "space": {"nameFr": "Espace", "color": "#1E90FF", "count": 4},
    "power": {"nameFr": "Énergie", "color": "#FFD700", "count": 3},
    "decoration": {"nameFr": "Décoration", "color": "#FF69B4", "count": 5},
    "utility": {"nameFr": "Utilitaires", "color": "#32CD32", "count": 15},
    "endgame": {"nameFr": "Endgame", "color": "#FF00FF", "count": 5},
    "world": {"nameFr": "Monde/Donjons", "color": "#228B22", "count": 5},
    "dimension": {"nameFr": "Dimensions", "color": "#8A2BE2", "count": 3},
    "automation": {"nameFr": "Automation", "color": "#4682B4", "count": 2},
    "logistics": {"nameFr": "Logistique", "color": "#20B2AA", "count": 1},
    "defense": {"nameFr": "Défense", "color": "#B22222", "count": 1},
    "armor": {"nameFr": "Armure", "color": "#C0C0C0", "count": 1},
    "redstone": {"nameFr": "Redstone", "color": "#DC143C", "count": 1}
  }
}
