{
  "metadata": {
    "version": "4.0.0",
    "lastUpdated": "2025-02-15",
    "totalMods": 270,
    "totalMachines": 2500,
    "textureSource": "https://github.com/GTNewHorizons"
  },
  "modList": [
    {"name": "GT5-Unofficial", "repo": "GT5-Unofficial", "category": "core", "machines": 500, "hasTextures": true, "description": "GregTech 5 - mod principal"},
    {"name": "GT++", "repo": "GTplusplus", "category": "core", "machines": 150, "hasTextures": true, "description": "Extension GregTech"},
    {"name": "NewHorizonsCoreMod", "repo": "NewHorizonsCoreMod", "category": "core", "machines": 50, "hasTextures": true, "description": "Core mod GTNH"},
    {"name": "GTNHLib", "repo": "GTNHLib", "category": "core", "machines": 0, "hasTextures": false, "description": "Librairie GTNH"},
    {"name": "Hodgepodge", "repo": "Hodgepodge", "category": "core", "machines": 0, "hasTextures": false, "description": "Fixes et optimisations"},
    {"name": "StructureLib", "repo": "StructureLib", "category": "core", "machines": 0, "hasTextures": false, "description": "Librairie structures"},
    {"name": "ModularUI", "repo": "ModularUI", "category": "core", "machines": 0, "hasTextures": false, "description": "Interface modulaire"},
    {"name": "ModularUI2", "repo": "ModularUI2", "category": "core", "machines": 0, "hasTextures": false, "description": "Interface modulaire v2"},
    {"name": "Angelica", "repo": "Angelica", "category": "core", "machines": 0, "hasTextures": false, "description": "Optimisations graphiques"},
    {"name": "AngelicaCompat", "repo": "AngelicaCompat", "category": "core", "machines": 0, "hasTextures": false, "description": "Compatibilité Angelica"},
    {"name": "CoreTweaks", "repo": "CoreTweaks", "category": "core", "machines": 0, "hasTextures": false, "description": "Tweaks système"},
    {"name": "UniMixins", "repo": "UniMixins", "category": "core", "machines": 0, "hasTextures": false, "description": "Mixins unifiés"},
    {"name": "BugTorch", "repo": "BugTorch", "category": "core", "machines": 0, "hasTextures": false, "description": "Fixes de bugs"},
    {"name": "FoamFix17", "repo": "FoamFix17", "category": "core", "machines": 0, "hasTextures": false, "description": "Optimisation mémoire"},
    {"name": "lwjgl3ify", "repo": "lwjgl3ify", "category": "core", "machines": 0, "hasTextures": false, "description": "Support LWJGL3"},

    {"name": "Applied Energistics 2", "repo": "Applied-Energistics-2-Unofficial", "category": "tech", "machines": 80, "hasTextures": true, "description": "Stockage et autocrafting ME"},
    {"name": "AE2 Stuff", "repo": "ae2stuff", "category": "tech", "machines": 10, "hasTextures": true, "description": "Extension AE2"},
    {"name": "AE2 Fluid Craft", "repo": "AE2FluidCraft-Rework", "category": "tech", "machines": 15, "hasTextures": true, "description": "Crafting fluides AE2"},
    {"name": "Not Enough Energistics", "repo": "NotEnoughEnergistics", "category": "tech", "machines": 5, "hasTextures": true, "description": "Interface NEI pour AE2"},
    {"name": "BetterP2P", "repo": "BetterP2P", "category": "tech", "machines": 5, "hasTextures": true, "description": "P2P amélioré"},
    {"name": "Wireless Crafting Terminal", "repo": "WirelessCraftingTerminal", "category": "tech", "machines": 5, "hasTextures": true, "description": "Terminal sans fil"},
    {"name": "Thaumic Energistics", "repo": "ThaumicEnergistics", "category": "tech", "machines": 20, "hasTextures": true, "description": "AE2 + Thaumcraft"},

    {"name": "EnderIO", "repo": "EnderIO", "category": "tech", "machines": 50, "hasTextures": true, "description": "Machines et conduits"},
    {"name": "EnderCore", "repo": "EnderCore", "category": "tech", "machines": 0, "hasTextures": false, "description": "Core EnderIO"},
    {"name": "Ender Storage", "repo": "EnderStorage", "category": "tech", "machines": 5, "hasTextures": true, "description": "Coffres ender"},
    {"name": "Ender Zoo", "repo": "EnderZoo", "category": "tech", "machines": 0, "hasTextures": false, "description": "Mobs de l'End"},

    {"name": "Buildcraft", "repo": "BuildCraft", "category": "tech", "machines": 35, "hasTextures": true, "description": "Pipes et machines"},
    {"name": "BuildCraftCompat", "repo": "BuildCraftCompat", "category": "tech", "machines": 0, "hasTextures": false, "description": "Compatibilité BuildCraft"},
    {"name": "BuildCraftOilTweak", "repo": "BuildCraftOilTweak", "category": "tech", "machines": 0, "hasTextures": false, "description": "Tweak pétrole"},

    {"name": "OpenComputers", "repo": "OpenComputers", "category": "tech", "machines": 40, "hasTextures": true, "description": "Ordinateurs programmables"},
    {"name": "Computronics", "repo": "Computronics", "category": "tech", "machines": 15, "hasTextures": true, "description": "Extension OpenComputers"},
    {"name": "OCGlasses", "repo": "OCGlasses", "category": "tech", "machines": 5, "hasTextures": true, "description": "Lunettes AR"},
    {"name": "OpenSecurity", "repo": "OpenSecurity", "category": "tech", "machines": 10, "hasTextures": true, "description": "Sécurité OC"},
    {"name": "OpenPrinter", "repo": "OpenPrinter", "category": "tech", "machines": 5, "hasTextures": true, "description": "Imprimante OC"},

    {"name": "Nuclear Control", "repo": "Nuclear-Control", "category": "tech", "machines": 15, "hasTextures": true, "description": "Moniteurs réacteurs"},
    {"name": "Nuclear Horizons", "repo": "NuclearHorizons", "category": "tech", "machines": 20, "hasTextures": true, "description": "Extension nucléaire"},
    {"name": "HBM Nuclear Tech", "repo": "Hbm-s-Nuclear-Tech-GIT", "category": "tech", "machines": 60, "hasTextures": true, "description": "Tech nucléaire avancée"},
    {"name": "Super Solar Panels", "repo": "supersolarpanels", "category": "tech", "machines": 15, "hasTextures": true, "description": "Panneaux solaires avancés"},

    {"name": "Logistics Pipes", "repo": "LogisticsPipes", "category": "tech", "machines": 35, "hasTextures": true, "description": "Système logistique"},
    {"name": "Steve's Factory Manager", "repo": "Steve-s-Factory-Manager", "category": "tech", "machines": 5, "hasTextures": true, "description": "Automation visuelle"},
    {"name": "Steve's Addons", "repo": "StevesAddons", "category": "tech", "machines": 5, "hasTextures": true, "description": "Extension SFM"},
    {"name": "RemoteIO", "repo": "RemoteIO", "category": "tech", "machines": 5, "hasTextures": true, "description": "IO à distance"},
    {"name": "Translocators", "repo": "Translocators", "category": "tech", "machines": 5, "hasTextures": true, "description": "Transfert items/fluides"},

    {"name": "Project Red", "repo": "ProjectRed", "category": "tech", "machines": 50, "hasTextures": true, "description": "Redstone amélioré"},
    {"name": "ProjectBlue", "repo": "ProjectBlue", "category": "tech", "machines": 10, "hasTextures": true, "description": "Extension Project Red"},
    {"name": "Wireless Redstone", "repo": "WirelessRedstone-CBE", "category": "tech", "machines": 10, "hasTextures": true, "description": "Redstone sans fil"},
    {"name": "QmunityLib", "repo": "QmunityLib", "category": "tech", "machines": 0, "hasTextures": false, "description": "Librairie PR"},

    {"name": "Twist Space Technology", "repo": "Twist-Space-Technology-Mod", "category": "tech", "machines": 40, "hasTextures": true, "description": "Tech spatiale"},
    {"name": "Matter Manipulator", "repo": "MatterManipulator", "category": "tech", "machines": 10, "hasTextures": true, "description": "Manipulation matière"},
    {"name": "Box++", "repo": "BoxPlusPlus", "category": "tech", "machines": 5, "hasTextures": true, "description": "Conteneurs"},
    {"name": "AFSU", "repo": "AFSU", "category": "tech", "machines": 5, "hasTextures": true, "description": "Stockage énergie"},
    {"name": "Hydro Energy", "repo": "HydroEnergy", "category": "tech", "machines": 10, "hasTextures": true, "description": "Énergie hydraulique"},

    {"name": "Thaumcraft", "repo": "Salis-Arcana", "category": "magic", "machines": 60, "hasTextures": true, "description": "Magie et aspects"},
    {"name": "Thaumic Tinkerer", "repo": "ThaumicTinkerer", "category": "magic", "machines": 25, "hasTextures": true, "description": "Extension Thaumcraft"},
    {"name": "Thaumic Exploration", "repo": "Thaumic_Exploration", "category": "magic", "machines": 15, "hasTextures": true, "description": "Extension Thaumcraft"},
    {"name": "Thaumic Bases", "repo": "ThaumicBases", "category": "magic", "machines": 15, "hasTextures": true, "description": "Extension Thaumcraft"},
    {"name": "Thaumic Horizons", "repo": "ThaumicHorizons", "category": "magic", "machines": 20, "hasTextures": true, "description": "Extension Thaumcraft"},
    {"name": "Thaumic Boots", "repo": "ThaumicBoots", "category": "magic", "machines": 5, "hasTextures": true, "description": "Bottes magiques"},
    {"name": "Thaumic Insurgence", "repo": "thaumicinsurgence", "category": "magic", "machines": 10, "hasTextures": true, "description": "Extension Thaumcraft"},
    {"name": "Forbidden Magic", "repo": "ForbiddenMagic", "category": "magic", "machines": 20, "hasTextures": true, "description": "Magie interdite"},
    {"name": "Tainted Magic", "repo": "Tainted-Magic", "category": "magic", "machines": 15, "hasTextures": true, "description": "Magie corrompue"},
    {"name": "Gadomancy", "repo": "Gadomancy", "category": "magic", "machines": 15, "hasTextures": true, "description": "Extension Thaumcraft"},
    {"name": "Witching Gadgets", "repo": "WitchingGadgets", "category": "magic", "machines": 20, "hasTextures": true, "description": "Gadgets magiques"},
    {"name": "Witchery Extras", "repo": "WitcheryExtras", "category": "magic", "machines": 10, "hasTextures": true, "description": "Extension Witchery"},
    {"name": "GTNH TC Wands", "repo": "GTNH-TC-Wands", "category": "magic", "machines": 5, "hasTextures": true, "description": "Baguettes"},
    {"name": "TCNEIAdditions", "repo": "TCNEIAdditions", "category": "magic", "machines": 0, "hasTextures": false, "description": "NEI Thaumcraft"},
    {"name": "TC Node Tracker", "repo": "TCNodeTracker", "category": "magic", "machines": 0, "hasTextures": false, "description": "Tracker de nodes"},
    {"name": "TC4Tweaks", "repo": "TC4Tweaks", "category": "magic", "machines": 0, "hasTextures": false, "description": "Tweaks Thaumcraft"},
    {"name": "Thaumcraft Research Tweaks", "repo": "thaumcraft-research-tweaks", "category": "magic", "machines": 0, "hasTextures": false, "description": "Tweaks recherche"},
    {"name": "Electro-Magic Tools", "repo": "Electro-Magic-Tools", "category": "magic", "machines": 15, "hasTextures": true, "description": "IC2 + Thaumcraft"},
    {"name": "Warp Theory", "repo": "WarpTheory", "category": "magic", "machines": 5, "hasTextures": true, "description": "Système warp"},

    {"name": "Botania", "repo": "Botania", "category": "magic", "machines": 55, "hasTextures": true, "description": "Magie des fleurs"},
    {"name": "Botanic Horizons", "repo": "Botanic-horizons", "category": "magic", "machines": 15, "hasTextures": true, "description": "Extension Botania"},
    {"name": "Advanced Botany", "repo": "Advanced-Botany", "category": "magic", "machines": 15, "hasTextures": true, "description": "Extension Botania"},

    {"name": "Blood Magic", "repo": "BloodMagic", "category": "magic", "machines": 35, "hasTextures": true, "description": "Magie du sang"},
    {"name": "Blood Arsenal", "repo": "BloodArsenal", "category": "magic", "machines": 15, "hasTextures": true, "description": "Extension Blood Magic"},

    {"name": "Astral Sorcery", "repo": "AstralSorcery", "category": "magic", "machines": 40, "hasTextures": true, "description": "Magie astrale"},

    {"name": "Draconic Evolution", "repo": "Draconic-Evolution", "category": "endgame", "machines": 30, "hasTextures": true, "description": "Tech draconic"},
    {"name": "BrandonsCore", "repo": "BrandonsCore", "category": "endgame", "machines": 0, "hasTextures": false, "description": "Core DE"},
    {"name": "Avaritia", "repo": "Avaritia", "category": "endgame", "machines": 20, "hasTextures": true, "description": "Endgame crafting"},
    {"name": "Avaritiaddons", "repo": "Avaritiaddons", "category": "endgame", "machines": 10, "hasTextures": true, "description": "Extension Avaritia"},
    {"name": "Universal Singularities", "repo": "Universal-Singularities", "category": "endgame", "machines": 5, "hasTextures": true, "description": "Singularités"},
    {"name": "Eternal Singularity", "repo": "Eternal-Singularity", "category": "endgame", "machines": 5, "hasTextures": true, "description": "Singularité éternelle"},

    {"name": "Tinkers Construct", "repo": "TinkersConstruct", "category": "tools", "machines": 30, "hasTextures": true, "description": "Outils moddables"},
    {"name": "Tinkerers Gregworks", "repo": "TinkersGregworks", "category": "tools", "machines": 10, "hasTextures": true, "description": "TiC + GregTech"},
    {"name": "Iguanas Tinkers Tweaks", "repo": "IguanaTweaksTConstruct", "category": "tools", "machines": 5, "hasTextures": true, "description": "Tweaks TiC"},
    {"name": "Super TiC", "repo": "Super-TiC", "category": "tools", "machines": 10, "hasTextures": true, "description": "Extension TiC"},
    {"name": "Tinkers Defense", "repo": "Tinkers-Defense", "category": "tools", "machines": 10, "hasTextures": true, "description": "Défense TiC"},
    {"name": "Tinkers Mechworks", "repo": "TinkersMechworks", "category": "tools", "machines": 15, "hasTextures": true, "description": "Mécanique TiC"},
    {"name": "TiC Tooltips", "repo": "TiC-Tooltips", "category": "tools", "machines": 0, "hasTextures": false, "description": "Tooltips TiC"},
    {"name": "Mantle", "repo": "Mantle", "category": "tools", "machines": 0, "hasTextures": false, "description": "Core TiC"},
    {"name": "Battlegear2", "repo": "Battlegear2-for-Backhand", "category": "tools", "machines": 5, "hasTextures": true, "description": "Dual wielding"},
    {"name": "Backhand", "repo": "Backhand", "category": "tools", "machines": 0, "hasTextures": false, "description": "Main gauche"},

    {"name": "Forestry", "repo": "ForestryMC", "category": "farming", "machines": 45, "hasTextures": true, "description": "Apiculture et arboriculture"},
    {"name": "Binnie's Mods", "repo": "Binnie", "category": "farming", "machines": 25, "hasTextures": true, "description": "Extension Forestry"},
    {"name": "Magic Bees", "repo": "MagicBees", "category": "farming", "machines": 15, "hasTextures": true, "description": "Abeilles magiques"},
    {"name": "Gendustry", "repo": "gendustry", "category": "farming", "machines": 20, "hasTextures": true, "description": "Génétique abeilles"},
    {"name": "BeeBetterAtBees", "repo": "BeeBetterAtBees-GTNH", "category": "farming", "machines": 0, "hasTextures": false, "description": "Aide abeilles"},
    {"name": "Crops++", "repo": "Crops-plus-plus", "category": "farming", "machines": 15, "hasTextures": true, "description": "Extension cultures"},
    {"name": "CropsNH", "repo": "CropsNH", "category": "farming", "machines": 10, "hasTextures": true, "description": "Crops GTNH"},
    {"name": "CropLoadCore", "repo": "CropLoadCore", "category": "farming", "machines": 0, "hasTextures": false, "description": "Core crops"},
    {"name": "Cooking For Blockheads", "repo": "CookingForBlockheads", "category": "farming", "machines": 15, "hasTextures": true, "description": "Cuisine"},
    {"name": "Spice of Life", "repo": "SpiceOfLife", "category": "farming", "machines": 5, "hasTextures": true, "description": "Variété alimentaire"},
    {"name": "Farming For Engineers", "repo": "FarmingForEngineers", "category": "farming", "machines": 5, "hasTextures": true, "description": "Agriculture tech"},
    {"name": "Nutrition", "repo": "Nutrition", "category": "farming", "machines": 0, "hasTextures": false, "description": "Système nutrition"},

    {"name": "Galacticraft", "repo": "Galacticraft", "category": "space", "machines": 50, "hasTextures": true, "description": "Exploration spatiale"},
    {"name": "Amun-Ra", "repo": "amunra", "category": "space", "machines": 35, "hasTextures": true, "description": "Planètes supplémentaires"},
    {"name": "Galaxia", "repo": "Galaxia", "category": "space", "machines": 30, "hasTextures": true, "description": "Extension Galacticraft"},
    {"name": "Personal Space", "repo": "PersonalSpace", "category": "space", "machines": 5, "hasTextures": true, "description": "Dimension personnelle"},

    {"name": "Railcraft", "repo": "Railcraft", "category": "transport", "machines": 40, "hasTextures": true, "description": "Trains et rails"},
    {"name": "SGCraft", "repo": "SGCraft", "category": "transport", "machines": 15, "hasTextures": true, "description": "Portes des étoiles"},
    {"name": "Sign Posts", "repo": "SignPosts", "category": "transport", "machines": 5, "hasTextures": true, "description": "Panneaux indicateurs"},
    {"name": "Navigator", "repo": "Navigator", "category": "transport", "machines": 0, "hasTextures": false, "description": "Navigation"},

    {"name": "Storage Drawers", "repo": "StorageDrawers", "category": "storage", "machines": 15, "hasTextures": true, "description": "Tiroirs de stockage"},
    {"name": "JABBA", "repo": "Jabba", "category": "storage", "machines": 10, "hasTextures": true, "description": "Barils de stockage"},
    {"name": "Iron Tanks", "repo": "Irontanks", "category": "storage", "machines": 12, "hasTextures": true, "description": "Réservoirs fer"},
    {"name": "Iron Tank Minecarts", "repo": "IronTankMinecarts", "category": "storage", "machines": 5, "hasTextures": true, "description": "Wagons réservoirs"},
    {"name": "Iron Chests", "repo": "ironchest", "category": "storage", "machines": 12, "hasTextures": true, "description": "Coffres métal"},
    {"name": "Iron Chest Minecarts", "repo": "IronChestMinecarts", "category": "storage", "machines": 5, "hasTextures": true, "description": "Wagons coffres"},
    {"name": "Better Storage", "repo": "BetterStorage", "category": "storage", "machines": 15, "hasTextures": true, "description": "Stockage amélioré"},
    {"name": "Backpack Mod", "repo": "Minecraft-Backpack-Mod", "category": "storage", "machines": 5, "hasTextures": true, "description": "Sacs à dos"},
    {"name": "Adventure Backpack", "repo": "AdventureBackpack2", "category": "storage", "machines": 5, "hasTextures": true, "description": "Sacs d'aventure"},
    {"name": "Sleeping Bags", "repo": "SleepingBags", "category": "storage", "machines": 3, "hasTextures": true, "description": "Sacs de couchage"},
    {"name": "Akashic Tome", "repo": "AkashicTome", "category": "storage", "machines": 1, "hasTextures": true, "description": "Livre universel"},

    {"name": "Twilight Forest", "repo": "twilightforest", "category": "dimension", "machines": 20, "hasTextures": true, "description": "Dimension Twilight"},
    {"name": "The Aether", "repo": "The-Aether-GTNH", "category": "dimension", "machines": 25, "hasTextures": true, "description": "Dimension céleste"},
    {"name": "Hardcore Ender Expansion", "repo": "Hardcore-Ender-Expansion", "category": "dimension", "machines": 25, "hasTextures": true, "description": "End amélioré"},
    {"name": "Roguelike Dungeons", "repo": "Roguelike-Dungeons", "category": "dimension", "machines": 0, "hasTextures": false, "description": "Donjons aléatoires"},

    {"name": "Chisel", "repo": "Chisel", "category": "decoration", "machines": 10, "hasTextures": true, "description": "Blocs décoratifs"},
    {"name": "ChiselTones", "repo": "ChiselTones", "category": "decoration", "machines": 5, "hasTextures": true, "description": "Sons Chisel"},
    {"name": "Ztones", "repo": "Ztones-Unofficial", "category": "decoration", "machines": 15, "hasTextures": true, "description": "Plus de blocs"},
    {"name": "Carpenters Blocks", "repo": "CarpentersBlocks", "category": "decoration", "machines": 20, "hasTextures": true, "description": "Blocs sculptables"},
    {"name": "Architecture Craft", "repo": "ArchitectureCraft", "category": "decoration", "machines": 15, "hasTextures": true, "description": "Architecture"},
    {"name": "Little Tiles", "repo": "LittleTiles", "category": "decoration", "machines": 10, "hasTextures": true, "description": "Micro-blocs"},
    {"name": "Malisis Doors", "repo": "MalisisDoors", "category": "decoration", "machines": 15, "hasTextures": true, "description": "Portes animées"},
    {"name": "Forge Multipart", "repo": "ForgeMultipart", "category": "decoration", "machines": 5, "hasTextures": true, "description": "Micro-blocs"},
    {"name": "Modern Markings", "repo": "ModernMarkings", "category": "decoration", "machines": 10, "hasTextures": true, "description": "Marquages"},

    {"name": "Open Blocks", "repo": "OpenBlocks", "category": "utility", "machines": 30, "hasTextures": true, "description": "Blocs utilitaires"},
    {"name": "OpenModsLib", "repo": "OpenModsLib", "category": "utility", "machines": 0, "hasTextures": false, "description": "Core OpenBlocks"},
    {"name": "Extra Utilities", "repo": "Extra-Utilities", "category": "utility", "machines": 35, "hasTextures": true, "description": "Utilitaires variés"},
    {"name": "Random Things", "repo": "Random-Things", "category": "utility", "machines": 25, "hasTextures": true, "description": "Choses aléatoires"},
    {"name": "Enhanced Loot Bags", "repo": "EnhancedLootBags", "category": "utility", "machines": 5, "hasTextures": true, "description": "Sacs de loot"},
    {"name": "Loot Games", "repo": "LootGames", "category": "utility", "machines": 5, "hasTextures": true, "description": "Mini-jeux"},
    {"name": "Find It", "repo": "FindIt", "category": "utility", "machines": 0, "hasTextures": false, "description": "Recherche blocs"},
    {"name": "Et Futurum", "repo": "Et-Futurum-Requiem", "category": "utility", "machines": 15, "hasTextures": true, "description": "Blocs futurs"},
    {"name": "Flood Lights", "repo": "FloodLights", "category": "utility", "machines": 10, "hasTextures": true, "description": "Projecteurs"},
    {"name": "Holo Inventory", "repo": "HoloInventory", "category": "utility", "machines": 5, "hasTextures": true, "description": "Inventaires holographiques"},
    {"name": "Vending Machine", "repo": "VendingMachine", "category": "utility", "machines": 3, "hasTextures": true, "description": "Distributeurs"},
    {"name": "Gravitation Suite", "repo": "Gravitation-Suite-Neo", "category": "utility", "machines": 8, "hasTextures": true, "description": "Suite gravitationnelle"},
    {"name": "Utilities In Excess", "repo": "UtilitiesInExcess", "category": "utility", "machines": 5, "hasTextures": true, "description": "Plus d'utilitaires"},
    {"name": "Random Boubles", "repo": "RandomBoubles", "category": "utility", "machines": 5, "hasTextures": true, "description": "Baubles aléatoires"},
    {"name": "Baubles Expanded", "repo": "Baubles-Expanded", "category": "utility", "machines": 5, "hasTextures": true, "description": "Plus de baubles"},
    {"name": "Server Utilities", "repo": "ServerUtilities", "category": "utility", "machines": 0, "hasTextures": false, "description": "Utilitaires serveur"},
    {"name": "WAWLA", "repo": "WAWLA", "category": "utility", "machines": 0, "hasTextures": false, "description": "What Are We Looking At"},

    {"name": "Open Modular Turrets", "repo": "OpenModularTurrets", "category": "defense", "machines": 20, "hasTextures": true, "description": "Tourelles modulaires"},
    {"name": "Infernal Mobs", "repo": "Infernal-Mobs", "category": "defense", "machines": 0, "hasTextures": false, "description": "Mobs difficiles"},
    {"name": "Special Mobs", "repo": "SpecialMobs", "category": "defense", "machines": 0, "hasTextures": false, "description": "Mobs spéciaux"},
    {"name": "Special AI", "repo": "SpecialAI", "category": "defense", "machines": 0, "hasTextures": false, "description": "IA améliorée"},
    {"name": "Too Much Loot", "repo": "TooMuchLoot", "category": "defense", "machines": 0, "hasTextures": false, "description": "Plus de loot"},

    {"name": "Natura", "repo": "Natura", "category": "world", "machines": 10, "hasTextures": true, "description": "Génération monde"},
    {"name": "Realistic Terrain Generation", "repo": "Realistic-Terrain-Generation", "category": "world", "machines": 0, "hasTextures": false, "description": "Terrain réaliste"},
    {"name": "Realistic World Gen", "repo": "Realistic-World-Gen", "category": "world", "machines": 0, "hasTextures": false, "description": "Monde réaliste"},
    {"name": "Climate Control", "repo": "Climate-Control", "category": "world", "machines": 0, "hasTextures": false, "description": "Contrôle climat"},
    {"name": "Default World Generator", "repo": "DefaultWorldGenerator", "category": "world", "machines": 0, "hasTextures": false, "description": "Générateur défaut"},
    {"name": "Biome Bridge", "repo": "BiomeBridge", "category": "world", "machines": 0, "hasTextures": false, "description": "Connexion biomes"},
    {"name": "Village Names", "repo": "VillageNames", "category": "world", "machines": 0, "hasTextures": false, "description": "Noms villages"},

    {"name": "Better Questing", "repo": "BetterQuesting", "category": "quests", "machines": 5, "hasTextures": true, "description": "Système quêtes"},
    {"name": "BQ3 Thermos Patch", "repo": "BQ3-Thermos-patch", "category": "quests", "machines": 0, "hasTextures": false, "description": "Patch Thermos"},
    {"name": "GTNH GuideBook", "repo": "GTNH-GuideBook-i18n", "category": "quests", "machines": 0, "hasTextures": false, "description": "Guide traduit"},
    {"name": "Guide API", "repo": "Guide-API", "category": "quests", "machines": 0, "hasTextures": false, "description": "API guides"},

    {"name": "Not Enough Items", "repo": "NotEnoughItems", "category": "interface", "machines": 0, "hasTextures": false, "description": "Recettes et items"},
    {"name": "NEI Addons", "repo": "neiaddons", "category": "interface", "machines": 0, "hasTextures": false, "description": "Extensions NEI"},
    {"name": "NEI Custom Diagram", "repo": "nei-custom-diagram", "category": "interface", "machines": 0, "hasTextures": false, "description": "Diagrammes NEI"},
    {"name": "NEI Integration", "repo": "NEI-Integration", "category": "interface", "machines": 0, "hasTextures": false, "description": "Intégration NEI"},
    {"name": "WAILA", "repo": "waila", "category": "interface", "machines": 0, "hasTextures": false, "description": "Info blocs"},
    {"name": "WAILA Harvestability", "repo": "WailaHarvestability", "category": "interface", "machines": 0, "hasTextures": false, "description": "Info récolte"},
    {"name": "WAILA Plugins", "repo": "WAILAPlugins", "category": "interface", "machines": 0, "hasTextures": false, "description": "Plugins WAILA"},
    {"name": "WDMla", "repo": "WDMla", "category": "interface", "machines": 0, "hasTextures": false, "description": "Extension WAILA"},
    {"name": "Journey Map", "repo": "journeymap-legacy", "category": "interface", "machines": 0, "hasTextures": false, "description": "Carte"},
    {"name": "Antique Atlas", "repo": "AntiqueAtlas", "category": "interface", "machines": 0, "hasTextures": false, "description": "Atlas antique"},
    {"name": "Schematica", "repo": "Schematica", "category": "interface", "machines": 0, "hasTextures": false, "description": "Schematics"},
    {"name": "Visual Prospecting", "repo": "VisualProspecting", "category": "interface", "machines": 2, "hasTextures": true, "description": "Prospection visuelle"},
    {"name": "InGame Info", "repo": "InGame-Info-XML", "category": "interface", "machines": 0, "hasTextures": false, "description": "Info en jeu"},
    {"name": "Mobs Info", "repo": "Mobs-Info", "category": "interface", "machines": 0, "hasTextures": false, "description": "Info mobs"},
    {"name": "Mouse Tweaks", "repo": "MouseTweaks", "category": "interface", "machines": 0, "hasTextures": false, "description": "Souris améliorée"},
    {"name": "Controlling", "repo": "Controlling", "category": "interface", "machines": 0, "hasTextures": false, "description": "Contrôles"},
    {"name": "Better Achievements", "repo": "BetterAchievements", "category": "interface", "machines": 0, "hasTextures": false, "description": "Succès améliorés"},
    {"name": "Better Loading Screen", "repo": "BetterLoadingScreen", "category": "interface", "machines": 0, "hasTextures": false, "description": "Écran chargement"},
    {"name": "Better Crashes", "repo": "BetterCrashes", "category": "interface", "machines": 0, "hasTextures": false, "description": "Meilleurs crashs"},
    {"name": "Overloaded Armor Bar", "repo": "OverloadedArmorBar", "category": "interface", "machines": 0, "hasTextures": false, "description": "Barre armure"},
    {"name": "Toro Health", "repo": "ToroHealth", "category": "interface", "machines": 0, "hasTextures": false, "description": "Barre santé"},
    {"name": "Dura Display", "repo": "DuraDisplay", "category": "interface", "machines": 0, "hasTextures": false, "description": "Durabilité"},
    {"name": "Just Enough Calculation", "repo": "JustEnoughCalculation", "category": "interface", "machines": 0, "hasTextures": false, "description": "Calculatrice"},
    {"name": "Fullscreen Windowed", "repo": "Fullscreen-Windowed-Minecraft", "category": "interface", "machines": 0, "hasTextures": false, "description": "Plein écran fenêtré"},
    {"name": "Custom Main Menu", "repo": "Custom-Main-Menu", "category": "interface", "machines": 0, "hasTextures": false, "description": "Menu personnalisé"},
    {"name": "Default Server List", "repo": "DefaultServerList", "category": "interface", "machines": 0, "hasTextures": false, "description": "Liste serveurs"},
    {"name": "Natures Compass", "repo": "NaturesCompass", "category": "interface", "machines": 1, "hasTextures": true, "description": "Boussole biomes"},
    {"name": "Not Enough Characters", "repo": "NotEnoughCharacters", "category": "interface", "machines": 0, "hasTextures": false, "description": "Support caractères"},
    {"name": "Share Where I Am", "repo": "Share-Where-I-am", "category": "interface", "machines": 0, "hasTextures": false, "description": "Partage position"},

    {"name": "CraftTweaker", "repo": "CraftTweaker", "category": "scripting", "machines": 0, "hasTextures": false, "description": "Modification recettes"},
    {"name": "ModTweaker", "repo": "ModTweaker", "category": "scripting", "machines": 0, "hasTextures": false, "description": "Extension CraftTweaker"},
    {"name": "MineTweaker GT5 Addon", "repo": "Minetweaker-Gregtech-5-Addon", "category": "scripting", "machines": 0, "hasTextures": false, "description": "MT pour GT5"},
    {"name": "ZenScript", "repo": "ZenScript", "category": "scripting", "machines": 0, "hasTextures": false, "description": "Langage scripting"},
    {"name": "AppleCore", "repo": "AppleCore", "category": "scripting", "machines": 0, "hasTextures": false, "description": "Core API"},

    {"name": "IFU", "repo": "IFU", "category": "misc", "machines": 5, "hasTextures": true, "description": "Interface Fluide Universel"},
    {"name": "Block Limiter", "repo": "BlockLimiter", "category": "misc", "machines": 0, "hasTextures": false, "description": "Limiteur blocs"},
    {"name": "GTSU", "repo": "GTSU", "category": "misc", "machines": 5, "hasTextures": true, "description": "Stockage GT"},
    {"name": "Nodal Mechanics", "repo": "Nodal-Mechanics", "category": "misc", "machines": 10, "hasTextures": true, "description": "Mécanique nodale"},
    {"name": "Anger Mod", "repo": "AngerMod", "category": "misc", "machines": 0, "hasTextures": false, "description": "Gestion colère"},
    {"name": "RecEx", "repo": "RecEx", "category": "misc", "machines": 0, "hasTextures": false, "description": "Recettes exportées"},
    {"name": "Opis", "repo": "Opis", "category": "misc", "machines": 0, "hasTextures": false, "description": "Profiling"},
    {"name": "Not Enough Production", "repo": "NotEnoughProduction", "category": "misc", "machines": 0, "hasTextures": false, "description": "Stats production"},
    {"name": "Prism", "repo": "Prism", "category": "misc", "machines": 0, "hasTextures": false, "description": "Effets visuels"},
    {"name": "bdlib", "repo": "bdlib", "category": "misc", "machines": 0, "hasTextures": false, "description": "Librairie"},
    {"name": "WanionLib", "repo": "WanionLib", "category": "misc", "machines": 0, "hasTextures": false, "description": "Librairie"},
    {"name": "AsieLib", "repo": "AsieLib", "category": "misc", "machines": 0, "hasTextures": false, "description": "Librairie"},
    {"name": "DummyCore", "repo": "DummyCore", "category": "misc", "machines": 0, "hasTextures": false, "description": "Core factice"},
    {"name": "Developer Capes", "repo": "DeveloperCapes", "category": "misc", "machines": 0, "hasTextures": false, "description": "Capes dev"},
    {"name": "Player API", "repo": "Player-API", "category": "misc", "machines": 0, "hasTextures": false, "description": "API joueur"},
    {"name": "Forgelin", "repo": "Forgelin", "category": "misc", "machines": 0, "hasTextures": false, "description": "Kotlin pour Forge"},
    {"name": "Code Chicken Core", "repo": "CodeChickenCore", "category": "misc", "machines": 0, "hasTextures": false, "description": "Core lib"},
    {"name": "Forge Relocation", "repo": "ForgeRelocation", "category": "misc", "machines": 5, "hasTextures": true, "description": "Relocalisation"},
    {"name": "Forge Relocation FMP", "repo": "ForgeRelocationFMP", "category": "misc", "machines": 0, "hasTextures": false, "description": "FMP compat"},
    {"name": "MrTJPCore", "repo": "MrTJPCore", "category": "misc", "machines": 0, "hasTextures": false, "description": "Core lib"},
    {"name": "Help Fixer", "repo": "HelpFixer", "category": "misc", "machines": 0, "hasTextures": false, "description": "Fix aide"},
    {"name": "Net Portal Fix", "repo": "NetherPortalFix", "category": "misc", "machines": 0, "hasTextures": false, "description": "Fix portails"},
    {"name": "Better Builders Wands", "repo": "BetterBuildersWands", "category": "misc", "machines": 5, "hasTextures": true, "description": "Baguettes construction"},
    {"name": "Craft Guide", "repo": "CraftGuide", "category": "misc", "machines": 0, "hasTextures": false, "description": "Guide craft"},
    {"name": "Lunatrius Core", "repo": "LunatriusCore", "category": "misc", "machines": 0, "hasTextures": false, "description": "Core lib"},
    {"name": "Enklume", "repo": "Enklume", "category": "misc", "machines": 1, "hasTextures": true, "description": "Enclume"},
    {"name": "Alchemical Grate", "repo": "AlchemyGrate", "category": "misc", "machines": 1, "hasTextures": true, "description": "Grille alchimique"},
    {"name": "Amazing Trophies", "repo": "Amazing-Trophies", "category": "misc", "machines": 5, "hasTextures": true, "description": "Trophées"},
    {"name": "Thaumcraft Mob Aspects", "repo": "ThaumcraftMobAspects", "category": "misc", "machines": 0, "hasTextures": false, "description": "Aspects mobs"},
    {"name": "World Edit GTNH", "repo": "worldedit-gtnh", "category": "misc", "machines": 0, "hasTextures": false, "description": "World Edit"},
    {"name": "BON2", "repo": "BON2", "category": "misc", "machines": 0, "hasTextures": false, "description": "Deobfuscateur"},
    {"name": "Block Renderer", "repo": "BlockRenderer6343", "category": "misc", "machines": 0, "hasTextures": false, "description": "Rendu blocs"},
    {"name": "TX Loader", "repo": "TX-Loader", "category": "misc", "machines": 0, "hasTextures": false, "description": "Chargeur textures"},
    {"name": "Not Enough IDs", "repo": "NotEnoughIds", "category": "misc", "machines": 0, "hasTextures": false, "description": "Plus d'IDs"},
    {"name": "Special Source", "repo": "SpecialSource", "category": "misc", "machines": 0, "hasTextures": false, "description": "Remapping"},
    {"name": "Spark", "repo": "spark", "category": "misc", "machines": 0, "hasTextures": false, "description": "Profiler"},
    {"name": "Postea", "repo": "Postea", "category": "misc", "machines": 0, "hasTextures": false, "description": "Post-processing"},
    {"name": "Tempora", "repo": "Tempora", "category": "misc", "machines": 0, "hasTextures": false, "description": "Temps"},
    {"name": "Inventory Bogo Sorter", "repo": "InventoryBogoSorter", "category": "misc", "machines": 0, "hasTextures": false, "description": "Tri inventaire"},
    {"name": "Foundation", "repo": "Foundation", "category": "misc", "machines": 0, "hasTextures": false, "description": "Core lib"},
    {"name": "Materials Lib", "repo": "MaterialsLib", "category": "misc", "machines": 0, "hasTextures": false, "description": "Librairie matériaux"},
    {"name": "Material Lib", "repo": "MaterialLib", "category": "misc", "machines": 0, "hasTextures": false, "description": "Librairie matériaux"},
    {"name": "Region Lib", "repo": "RegionLib", "category": "misc", "machines": 0, "hasTextures": false, "description": "Librairie régions"},
    {"name": "Darkerer", "repo": "Darkerer", "category": "misc", "machines": 0, "hasTextures": false, "description": "Mode sombre"},
    {"name": "Pseudo", "repo": "Pseudo", "category": "misc", "machines": 0, "hasTextures": false, "description": "Pseudonyme"},
    {"name": "Nood", "repo": "Nood", "category": "misc", "machines": 0, "hasTextures": false, "description": "Utilitaire"},
    {"name": "Tracing", "repo": "tracing", "category": "misc", "machines": 0, "hasTextures": false, "description": "Traçage"},
    {"name": "Jar Jar", "repo": "JarJar", "category": "misc", "machines": 0, "hasTextures": false, "description": "Packaging"},
    {"name": "Jabel", "repo": "jabel", "category": "misc", "machines": 0, "hasTextures": false, "description": "Java backport"},
    {"name": "Jabel Stubs", "repo": "jabel-stubs", "category": "misc", "machines": 0, "hasTextures": false, "description": "Stubs Jabel"}
  ],
  "textureUrls": {
    "gregtech": "https://raw.githubusercontent.com/GTNewHorizons/GT5-Unofficial/master/src/main/resources/assets/gregtech/textures/blocks/iconsets/",
    "ae2": "https://raw.githubusercontent.com/GTNewHorizons/Applied-Energistics-2-Unofficial/master/src/main/resources/assets/appliedenergistics2/textures/blocks/",
    "tinkers": "https://raw.githubusercontent.com/GTNewHorizons/TinkersConstruct/master/src/main/resources/assets/tinker/textures/blocks/",
    "enderio": "https://raw.githubusercontent.com/GTNewHorizons/EnderIO/master/src/main/resources/assets/enderio/textures/blocks/",
    "forestry": "https://raw.githubusercontent.com/GTNewHorizons/ForestryMC/master/src/main/resources/assets/forestry/textures/blocks/",
    "railcraft": "https://raw.githubusercontent.com/GTNewHorizons/Railcraft/master/src/main/resources/assets/railcraft/textures/blocks/",
    "galacticraft": "https://raw.githubusercontent.com/GTNewHorizons/Galacticraft/master/src/main/resources/assets/galacticraftcore/textures/blocks/",
    "bloodmagic": "https://raw.githubusercontent.com/GTNewHorizons/BloodMagic/master/src/main/resources/assets/alchemicalwizardry/textures/blocks/",
    "botania": "https://raw.githubusercontent.com/GTNewHorizons/Botania/master/src/main/resources/assets/botania/textures/blocks/",
    "thaumcraft": "https://raw.githubusercontent.com/GTNewHorizons/Salis-Arcana/master/src/main/resources/assets/thaumcraft/textures/blocks/",
    "draconic": "https://raw.githubusercontent.com/GTNewHorizons/Draconic-Evolution/master/src/main/resources/assets/draconicevolution/textures/blocks/",
    "opencomputers": "https://raw.githubusercontent.com/GTNewHorizons/OpenComputers/master/src/main/resources/assets/opencomputers/textures/blocks/",
    "buildcraft": "https://raw.githubusercontent.com/GTNewHorizons/BuildCraft/master/src/main/resources/assets/buildcraft/textures/blocks/",
    "twilightforest": "https://raw.githubusercontent.com/GTNewHorizons/twilightforest/master/src/main/resources/assets/twilightforest/textures/blocks/",
    "hbm": "https://raw.githubusercontent.com/GTNewHorizons/Hbm-s-Nuclear-Tech-GIT/master/src/main/resources/assets/hbm/textures/blocks/"
  },
  "categories": {
    "core": {"nameFr": "Mods Principaux", "color": "#FF6600", "count": 15},
    "tech": {"nameFr": "Technologie", "color": "#00BFFF", "count": 55},
    "magic": {"nameFr": "Magie", "color": "#9400D3", "count": 25},
    "tools": {"nameFr": "Outils", "color": "#FF4500", "count": 10},
    "farming": {"nameFr": "Agriculture/Abeilles", "color": "#8B4513", "count": 12},
    "storage": {"nameFr": "Stockage", "color": "#DAA520", "count": 11},
    "transport": {"nameFr": "Transport", "color": "#696969", "count": 4},
    "space": {"nameFr": "Espace", "color": "#1E90FF", "count": 4},
    "decoration": {"nameFr": "Décoration", "color": "#FF69B4", "count": 9},
    "utility": {"nameFr": "Utilitaires", "color": "#32CD32", "count": 17},
    "endgame": {"nameFr": "Endgame", "color": "#FF00FF", "count": 6},
    "dimension": {"nameFr": "Dimensions", "color": "#8A2BE2", "count": 4},
    "world": {"nameFr": "Monde/Génération", "color": "#228B22", "count": 7},
    "defense": {"nameFr": "Défense/Mobs", "color": "#B22222", "count": 5},
    "quests": {"nameFr": "Quêtes/Guides", "color": "#FFD700", "count": 4},
    "interface": {"nameFr": "Interface", "color": "#4682B4", "count": 25},
    "scripting": {"nameFr": "Scripting", "color": "#DC143C", "count": 5},
    "misc": {"nameFr": "Divers/Librairies", "color": "#808080", "count": 55}
  }
}
